mantium_spec/__init__.py
mantium_spec/api/__init__.py
mantium_spec/api/applications_api.py
mantium_spec/api_client.py
mantium_spec/configuration.py
mantium_spec/exceptions.py
mantium_spec/models/__init__.py
mantium_spec/models/answer.py
mantium_spec/models/answer_meta.py
mantium_spec/models/api_data_source_type.py
mantium_spec/models/application_chat_response.py
mantium_spec/models/application_credential.py
mantium_spec/models/application_detail_response.py
mantium_spec/models/application_query_request.py
mantium_spec/models/application_query_response.py
mantium_spec/models/application_response.py
mantium_spec/models/application_status.py
mantium_spec/models/application_top_k_query_request.py
mantium_spec/models/chat_answer.py
mantium_spec/models/chat_config.py
mantium_spec/models/chat_gpt_plugin_application_detail_response.py
mantium_spec/models/citation.py
mantium_spec/models/content_creation_template_options.py
mantium_spec/models/content_type.py
mantium_spec/models/credential_type.py
mantium_spec/models/cursor_datamodel_page_application_response.py
mantium_spec/models/custom_template_options.py
mantium_spec/models/customer_support_template_options.py
mantium_spec/models/data_source_type.py
mantium_spec/models/data_sources_inner.py
mantium_spec/models/document.py
mantium_spec/models/document_metadata.py
mantium_spec/models/event_planning_template_options.py
mantium_spec/models/gitlab_data_source_details.py
mantium_spec/models/gitlab_project_info.py
mantium_spec/models/http_validation_error.py
mantium_spec/models/legal_documents_template_options.py
mantium_spec/models/location_inner.py
mantium_spec/models/mantium_retriever_tool.py
mantium_spec/models/mantium_retriever_tool_config.py
mantium_spec/models/meeting_info_template_options.py
mantium_spec/models/moderation.py
mantium_spec/models/moderation_config.py
mantium_spec/models/moderation_level.py
mantium_spec/models/personal_knowledge_management_template_options.py
mantium_spec-1.0.1108.dist-info/WHEEL
mantium_spec-1.0.1108.dist-info/METADATA
mantium_spec-1.0.1108.dist-info/RECORD
