Metadata-Version: 2.1
Name: mantium-spec
Version: 1.0.1108
Summary: OpenAPI-generated Python client
Author: Mantium
Author-email: support@mantiumai.com
Requires-Python: >=3.7
Classifier: Programming Language :: Python :: 3
Classifier: Programming Language :: Python :: 3.7
Classifier: Programming Language :: Python :: 3.8
Classifier: Programming Language :: Python :: 3.9
Classifier: Programming Language :: Python :: 3.10
Classifier: Programming Language :: Python :: 3.11
Requires-Dist: openapi-client (>=1.1.7,<2.0.0)
